Metadata-Version: 2.1
Name: biomodules
Version: 1.1.18
Summary: bioinformatics modules.
Home-page: https://github.com/lawley0316/biomodules
Author: Lawley
Author-email: lawley0316@gmail.com
License: MIT
Classifier: License :: OSI Approved :: MIT License
Classifier: Programming Language :: Python
Classifier: Programming Language :: Python :: 3
Classifier: Programming Language :: Python :: 3.6
Classifier: Programming Language :: Python :: Implementation :: CPython
Classifier: Programming Language :: Python :: Implementation :: PyPy
Requires-Python: >=3.6.0
Requires-Dist: okmodule
Requires-Dist: biopython
Provides-Extra: ont
Requires-Dist: medaka; extra == "ont"
